{
  "$schema": "https://ui.shadcn.com/schema/registry-item.json",
  "name": "comet-card",
  "type": "registry:ui",
  "title": "Comet Card",
  "description": "A card with hover tilt, depth translation, and glare.",
  "dependencies": [
    "motion"
  ],
  "files": [
    {
      "path": "src/components/magicui/comet-card.tsx",
      "content": "'use client'\n\nimport { useRef, type MouseEvent, type ReactNode } from 'react'\nimport {\n  motion,\n  useMotionTemplate,\n  useMotionValue,\n  useSpring,\n  useTransform,\n} from 'motion/react'\nimport { cn } from '@/lib/utils'\n\ninterface CometCardProps {\n  rotateDepth?: number\n  translateDepth?: number\n  className?: string\n  cardClassName?: string\n  children: ReactNode\n}\n\nexport function CometCard({\n  rotateDepth = 17.5,\n  translateDepth = 20,\n  className,\n  cardClassName,\n  children,\n}: CometCardProps) {\n  const ref = useRef<HTMLDivElement>(null)\n  const x = useMotionValue(0)\n  const y = useMotionValue(0)\n  const mouseXSpring = useSpring(x)\n  const mouseYSpring = useSpring(y)\n\n  const rotateX = useTransform(\n    mouseYSpring,\n    [-0.5, 0.5],\n    [`-${rotateDepth}deg`, `${rotateDepth}deg`]\n  )\n  const rotateY = useTransform(\n    mouseXSpring,\n    [-0.5, 0.5],\n    [`${rotateDepth}deg`, `-${rotateDepth}deg`]\n  )\n  const translateX = useTransform(\n    mouseXSpring,\n    [-0.5, 0.5],\n    [`-${translateDepth}px`, `${translateDepth}px`]\n  )\n  const translateY = useTransform(\n    mouseYSpring,\n    [-0.5, 0.5],\n    [`${translateDepth}px`, `-${translateDepth}px`]\n  )\n  const glareX = useTransform(mouseXSpring, [-0.5, 0.5], [0, 100])\n  const glareY = useTransform(mouseYSpring, [-0.5, 0.5], [0, 100])\n  const glareBackground = useMotionTemplate`radial-gradient(circle at ${glareX}% ${glareY}%, rgba(255,255,255,0.9) 10%, rgba(255,255,255,0.65) 20%, rgba(255,255,255,0) 80%)`\n\n  const handleMouseMove = (event: MouseEvent<HTMLDivElement>) => {\n    if (!ref.current) return\n\n    const rect = ref.current.getBoundingClientRect()\n    x.set((event.clientX - rect.left) / rect.width - 0.5)\n    y.set((event.clientY - rect.top) / rect.height - 0.5)\n  }\n\n  return (\n    <div className={cn('[perspective:1200px] [transform-style:preserve-3d]', className)}>\n      <motion.div\n        ref={ref}\n        onMouseMove={handleMouseMove}\n        onMouseLeave={() => {\n          x.set(0)\n          y.set(0)\n        }}\n        initial={{ scale: 1, z: 0 }}\n        whileHover={{ scale: 1.05, z: 50, transition: { duration: 0.2 } }}\n        className={cn(\n          'relative overflow-hidden rounded-2xl border border-zinc-200 bg-white p-6 shadow-[0_24px_70px_-44px_rgba(24,24,27,0.55)] dark:border-zinc-800 dark:bg-zinc-950',\n          cardClassName\n        )}\n        style={{\n          rotateX,\n          rotateY,\n          translateX,\n          translateY,\n          boxShadow:\n            'rgba(0,0,0,0.08) 0px 36px 70px -42px, rgba(0,0,0,0.18) 0px 18px 38px -30px',\n        }}\n      >\n        {children}\n        <motion.div\n          className=\"pointer-events-none absolute inset-0 z-50 h-full w-full rounded-[inherit] mix-blend-overlay\"\n          style={{ background: glareBackground, opacity: 0.6 }}\n        />\n      </motion.div>\n    </div>\n  )\n}\n",
      "type": "registry:ui"
    }
  ]
}
