{
  "$schema": "https://ui.shadcn.com/schema/registry-item.json",
  "name": "floating-dock",
  "type": "registry:ui",
  "title": "Floating Dock",
  "description": "A responsive dock with icon magnification and labels.",
  "dependencies": [
    "motion"
  ],
  "files": [
    {
      "path": "src/components/magicui/floating-dock.tsx",
      "content": "'use client'\n\nimport { useRef, useState, type ReactNode } from 'react'\nimport {\n  AnimatePresence,\n  motion,\n  useMotionValue,\n  useSpring,\n  useTransform,\n  type MotionValue,\n} from 'motion/react'\nimport { cn } from '@/lib/utils'\n\nexport interface FloatingDockItem {\n  title: string\n  icon: ReactNode\n  href?: string\n  onClick?: () => void\n}\n\ninterface FloatingDockProps {\n  items: FloatingDockItem[]\n  className?: string\n  desktopClassName?: string\n  mobileClassName?: string\n}\n\nexport function FloatingDock({\n  items,\n  className,\n  desktopClassName,\n  mobileClassName,\n}: FloatingDockProps) {\n  return (\n    <div className={className}>\n      <FloatingDockDesktop items={items} className={desktopClassName} />\n      <FloatingDockMobile items={items} className={mobileClassName} />\n    </div>\n  )\n}\n\nfunction FloatingDockMobile({\n  items,\n  className,\n}: {\n  items: FloatingDockItem[]\n  className?: string\n}) {\n  const [open, setOpen] = useState(false)\n\n  return (\n    <div className={cn('relative block md:hidden', className)}>\n      <AnimatePresence>\n        {open ? (\n          <motion.div\n            layoutId=\"floating-dock-mobile-nav\"\n            className=\"absolute inset-x-0 bottom-full mb-2 flex flex-col gap-2\"\n          >\n            {items.map((item, index) => (\n              <motion.div\n                key={item.title}\n                initial={{ opacity: 0, y: 10 }}\n                animate={{ opacity: 1, y: 0 }}\n                exit={{ opacity: 0, y: 10, transition: { delay: index * 0.05 } }}\n                transition={{ delay: (items.length - 1 - index) * 0.05 }}\n              >\n                <DockAction\n                  item={item}\n                  className=\"flex h-10 w-10 items-center justify-center rounded-full bg-zinc-100 text-zinc-600 dark:bg-zinc-900 dark:text-zinc-300\"\n                >\n                  <span className=\"h-4 w-4\">{item.icon}</span>\n                </DockAction>\n              </motion.div>\n            ))}\n          </motion.div>\n        ) : null}\n      </AnimatePresence>\n      <button\n        type=\"button\"\n        onClick={() => setOpen((current) => !current)}\n        className=\"flex h-10 w-10 items-center justify-center rounded-full bg-zinc-100 text-zinc-500 dark:bg-zinc-900 dark:text-zinc-400\"\n        aria-expanded={open}\n        aria-label=\"Toggle dock\"\n      >\n        <svg aria-hidden=\"true\" viewBox=\"0 0 24 24\" className=\"h-5 w-5\" fill=\"none\">\n          <path\n            d=\"M6 9h12M8 13h8M10 17h4\"\n            stroke=\"currentColor\"\n            strokeWidth=\"2\"\n            strokeLinecap=\"round\"\n          />\n        </svg>\n      </button>\n    </div>\n  )\n}\n\nfunction FloatingDockDesktop({\n  items,\n  className,\n}: {\n  items: FloatingDockItem[]\n  className?: string\n}) {\n  const mouseX = useMotionValue(Infinity)\n\n  return (\n    <motion.div\n      onMouseMove={(event) => mouseX.set(event.clientX)}\n      onMouseLeave={() => mouseX.set(Infinity)}\n      className={cn(\n        'mx-auto hidden h-16 items-end gap-4 rounded-2xl bg-zinc-100 px-4 pb-3 md:flex dark:bg-zinc-900',\n        className\n      )}\n    >\n      {items.map((item) => (\n        <IconContainer key={item.title} mouseX={mouseX} item={item} />\n      ))}\n    </motion.div>\n  )\n}\n\nfunction IconContainer({\n  mouseX,\n  item,\n}: {\n  mouseX: MotionValue<number>\n  item: FloatingDockItem\n}) {\n  const ref = useRef<HTMLDivElement>(null)\n  const [hovered, setHovered] = useState(false)\n\n  const distance = useTransform(mouseX, (value) => {\n    const bounds = ref.current?.getBoundingClientRect() ?? { x: 0, width: 0 }\n    return value - bounds.x - bounds.width / 2\n  })\n  const width = useSpring(useTransform(distance, [-150, 0, 150], [40, 80, 40]), {\n    mass: 0.1,\n    stiffness: 150,\n    damping: 12,\n  })\n  const height = useSpring(useTransform(distance, [-150, 0, 150], [40, 80, 40]), {\n    mass: 0.1,\n    stiffness: 150,\n    damping: 12,\n  })\n  const iconWidth = useSpring(useTransform(distance, [-150, 0, 150], [20, 40, 20]), {\n    mass: 0.1,\n    stiffness: 150,\n    damping: 12,\n  })\n  const iconHeight = useSpring(useTransform(distance, [-150, 0, 150], [20, 40, 20]), {\n    mass: 0.1,\n    stiffness: 150,\n    damping: 12,\n  })\n\n  return (\n    <DockAction item={item}>\n      <motion.div\n        ref={ref}\n        style={{ width, height }}\n        onMouseEnter={() => setHovered(true)}\n        onMouseLeave={() => setHovered(false)}\n        className=\"relative flex aspect-square items-center justify-center rounded-full bg-zinc-200 text-zinc-700 dark:bg-zinc-800 dark:text-zinc-200\"\n      >\n        <AnimatePresence>\n          {hovered ? (\n            <motion.div\n              initial={{ opacity: 0, y: 10, x: '-50%' }}\n              animate={{ opacity: 1, y: 0, x: '-50%' }}\n              exit={{ opacity: 0, y: 2, x: '-50%' }}\n              className=\"absolute -top-8 left-1/2 w-fit whitespace-pre rounded-md border border-zinc-200 bg-zinc-100 px-2 py-0.5 text-xs text-zinc-700 dark:border-zinc-800 dark:bg-zinc-950 dark:text-white\"\n            >\n              {item.title}\n            </motion.div>\n          ) : null}\n        </AnimatePresence>\n        <motion.div style={{ width: iconWidth, height: iconHeight }} className=\"flex items-center justify-center\">\n          {item.icon}\n        </motion.div>\n      </motion.div>\n    </DockAction>\n  )\n}\n\nfunction DockAction({\n  item,\n  children,\n  className,\n}: {\n  item: FloatingDockItem\n  children: ReactNode\n  className?: string\n}) {\n  if (item.href) {\n    return (\n      <a href={item.href} aria-label={item.title} className={className}>\n        {children}\n      </a>\n    )\n  }\n\n  return (\n    <button type=\"button\" onClick={item.onClick} aria-label={item.title} className={className}>\n      {children}\n    </button>\n  )\n}\n",
      "type": "registry:ui"
    }
  ]
}
